nmtscore/__init__.py
nmtscore/scorer.py
nmtscore/models/__init__.py
nmtscore/models/m2m100.py
nmtscore/models/prism.py
nmtscore/models/small100.py
nmtscore/models/tokenization_small100.py
nmtscore/models/utils.py
nmtscore-0.3.3.dist-info/LICENSE
nmtscore-0.3.3.dist-info/METADATA
nmtscore-0.3.3.dist-info/WHEEL
nmtscore-0.3.3.dist-info/top_level.txt
nmtscore-0.3.3.dist-info/RECORD
