Metadata-Version: 2.1
Name: nmtscore
Version: 0.3.3
Summary: A library of translation-based text similarity measures
Home-page: https://github.com/ZurichNLP/nmtscore
Author: Jannis Vamvas
Author-email: vamvas@cl.uzh.ch
Project-URL: Bug Tracker, https://github.com/ZurichNLP/nmtscore/issues
Classifier: Programming Language :: Python :: 3
Classifier: License :: OSI Approved :: MIT License
Classifier: Operating System :: OS Independent
Requires-Python: >=3.8
License-File: LICENSE
Requires-Dist: transformers <4.34
Requires-Dist: sentencepiece
Requires-Dist: tqdm
Requires-Dist: sqlitedict
Provides-Extra: prism
Requires-Dist: fairseq <=0.10.0 ; extra == 'prism'
Requires-Dist: numpy <1.24 ; extra == 'prism'
